.env
.gitignore
Dockerfile
LICENSE
README.md
compose.yml
mkdocs.yml
requirements.txt
setup.py
.github/workflows/ci.yml
docs/ObsidianVault/Concept.md
docs/ObsidianVault/Docker.md
docs/ObsidianVault/Installation.md
docs/ObsidianVault/References.md
docs/ObsidianVault/index.md
docs/ObsidianVault/Usage/ECharts.md
docs/ObsidianVault/Usage/Setup.md
docs/ObsidianVault/assets/javascripts/interactive_graph.js
docs/ObsidianVault/assets/javascripts/obsidian_tags.js
docs/ObsidianVault/assets/stylesheets/interactive_graph.css
docs/ObsidianVault/assets/stylesheets/obsidian_tags.css
mkdocs_obsidian_interactive_graph_plugin.egg-info/PKG-INFO
mkdocs_obsidian_interactive_graph_plugin.egg-info/SOURCES.txt
mkdocs_obsidian_interactive_graph_plugin.egg-info/dependency_links.txt
mkdocs_obsidian_interactive_graph_plugin.egg-info/entry_points.txt
mkdocs_obsidian_interactive_graph_plugin.egg-info/requires.txt
mkdocs_obsidian_interactive_graph_plugin.egg-info/top_level.txt
obsidian_interactive_graph/__init__.py
obsidian_interactive_graph/plugin.py